pkg/__init__.py
aiuv-0.9.dist-info/Licence.txt
aiuv-0.9.dist-info/METADATA
aiuv-0.9.dist-info/WHEEL
aiuv-0.9.dist-info/top_level.txt
aiuv-0.9.dist-info/RECORD
