Metadata-Version: 2.1
Name: aiuv
Version: 0.9
Summary: This is the package with all the ai codes
Author: Yuvraj
License-File: Licence.txt
